md2pdfy/__init__.py
md2pdfy/main.py
md2pdfy-0.0.3.dist-info/LICENSE.txt
md2pdfy-0.0.3.dist-info/METADATA
md2pdfy-0.0.3.dist-info/WHEEL
md2pdfy-0.0.3.dist-info/entry_points.txt
md2pdfy-0.0.3.dist-info/top_level.txt
md2pdfy-0.0.3.dist-info/RECORD
