Metadata-Version: 2.1
Name: md2pdfy
Version: 0.0.3
Summary: Convert markdown files into PDF format
Home-page: https://github.com/lnadi17/md2pdfy
Author: Luka Nadiradze
Author-email: lnadi17@freeuni.edu.ge
License: UNKNOWN
Platform: UNKNOWN
Classifier: Programming Language :: Python :: 3
Classifier: License :: OSI Approved :: MIT License
Classifier: Operating System :: OS Independent
Requires-Python: >=3.6
Requires-Dist: pdfy (>=1.1.0)
Requires-Dist: selenium (>=3.141.0)
Requires-Dist: webdriver-manager (>=3.3.0)
Requires-Dist: Markdown (>=3.3.3)
Requires-Dist: beautifulsoup4
Requires-Dist: PyPDF2 (>=1.26.0)
